lusid_scheduler/__init__.py
lusid_scheduler/__version__.py
lusid_scheduler/api_client.py
lusid_scheduler/configuration.py
lusid_scheduler/exceptions.py
lusid_scheduler/rest.py
lusid_scheduler/api/__init__.py
lusid_scheduler/api/application_metadata_api.py
lusid_scheduler/api/images_api.py
lusid_scheduler/api/jobs_api.py
lusid_scheduler/api/schedules_api.py
lusid_scheduler/models/__init__.py
lusid_scheduler/models/access_controlled_action.py
lusid_scheduler/models/access_controlled_resource.py
lusid_scheduler/models/action_id.py
lusid_scheduler/models/argument_definition.py
lusid_scheduler/models/create_job_request.py
lusid_scheduler/models/create_schedule_request.py
lusid_scheduler/models/id_selector_definition.py
lusid_scheduler/models/identifier_part_schema.py
lusid_scheduler/models/image.py
lusid_scheduler/models/image_summary.py
lusid_scheduler/models/job_definition.py
lusid_scheduler/models/job_history.py
lusid_scheduler/models/job_run_result.py
lusid_scheduler/models/link.py
lusid_scheduler/models/lusid_problem_details.py
lusid_scheduler/models/lusid_validation_problem_details.py
lusid_scheduler/models/notification.py
lusid_scheduler/models/repository.py
lusid_scheduler/models/required_resources.py
lusid_scheduler/models/resource_id.py
lusid_scheduler/models/resource_list_of_access_controlled_resource.py
lusid_scheduler/models/resource_list_of_image_summary.py
lusid_scheduler/models/resource_list_of_job_definition.py
lusid_scheduler/models/resource_list_of_job_history.py
lusid_scheduler/models/resource_list_of_repository.py
lusid_scheduler/models/resource_list_of_schedule_definition.py
lusid_scheduler/models/scan_report.py
lusid_scheduler/models/scan_summary.py
lusid_scheduler/models/schedule_definition.py
lusid_scheduler/models/start_job_request.py
lusid_scheduler/models/start_job_response.py
lusid_scheduler/models/start_schedule_response.py
lusid_scheduler/models/tag.py
lusid_scheduler/models/time_trigger.py
lusid_scheduler/models/trigger.py
lusid_scheduler_sdk_preview-0.0.829.dist-info/METADATA
lusid_scheduler_sdk_preview-0.0.829.dist-info/WHEEL
lusid_scheduler_sdk_preview-0.0.829.dist-info/top_level.txt
lusid_scheduler_sdk_preview-0.0.829.dist-info/RECORD
