Metadata-Version: 2.1
Name: lusid-scheduler-sdk-preview
Version: 0.0.829
Summary: Python Preview SDK for Scheduler API
Home-page: https://github.com/finbourne/lusid-scheduler-sdk-python-preview
Author: FINBOURNE Technology
Author-email: engineering@finbourne.com
License: MIT
Keywords: OpenAPI,FINBOURNE,LUSID,Notifications API
Platform: UNKNOWN
Requires-Dist: urllib3 (>=1.15)
Requires-Dist: six (>=1.10)
Requires-Dist: certifi (>=14.05.14)
Requires-Dist: python-dateutil (>=2.5.3)
Requires-Dist: urllib3 (>=1.15.1)
Requires-Dist: requests (>=2.21.0)
Requires-Dist: finbourne-sdk-utilities (>=0.0.10)
